{
    "$schema": "http://json-schema.org/draft-07/schema#",
    "type": "object",
    "title": "Output Schema for copy Operation",
    "description": "Output schema for the copy operation in the connector.",
    "properties": {
        "payload": {
            "type": "object",
            "description": "The main response payload from the copy operation."
        },
        "attributes": {
            "type": "object",
            "description": "Metadata about the copy operation.",
            "properties": {},
            "additionalProperties": false
        }
    },
    "required": [
        "payload",
        "attributes"
    ],
    "additionalProperties": false
}